commonware/__init__.py
commonware/decorators.py
commonware/middleware.py
commonware/exceptions/__init__.py
commonware/exceptions/middleware.py
commonware/exceptions/tests.py
commonware/log/__init__.py
commonware/log/middleware.py
commonware/log/tests.py
commonware/request/__init__.py
commonware/request/middleware.py
commonware/request/tests.py
commonware/response/__init__.py
commonware/response/decorators.py
commonware/response/middleware.py
commonware/response/tests.py
commonware/response/cookies/__init__.py
commonware/response/cookies/models.py
commonware/response/cookies/monkeypatch.py
commonware/response/cookies/tests.py
commonware/session/__init__.py
commonware/session/middleware.py
commonware-0.6.0.dist-info/LICENSE
commonware-0.6.0.dist-info/METADATA
commonware-0.6.0.dist-info/WHEEL
commonware-0.6.0.dist-info/top_level.txt
commonware-0.6.0.dist-info/RECORD
